CtfAllInOne2018124/README.md
CtfAllInOne2018124/__init__.py
CtfAllInOne2018124/__main__.py
CtfAllInOne2018124/file.epub
CtfAllInOne2018124/index.html
CtfAllInOne2018124/css/__init__.py
CtfAllInOne2018124/css/annotations.css
CtfAllInOne2018124/css/main.css
CtfAllInOne2018124/css/normalize.css
CtfAllInOne2018124/css/popup.css
CtfAllInOne2018124/font/__init__.py
CtfAllInOne2018124/font/fontello.eot
CtfAllInOne2018124/font/fontello.svg
CtfAllInOne2018124/font/fontello.ttf
CtfAllInOne2018124/font/fontello.woff
CtfAllInOne2018124/img/__init__.py
CtfAllInOne2018124/img/annotator-glyph-sprite.png
CtfAllInOne2018124/img/annotator-icon-sprite.png
CtfAllInOne2018124/img/apple-touch-icon.png
CtfAllInOne2018124/img/cancelfullscreen.png
CtfAllInOne2018124/img/close.png
CtfAllInOne2018124/img/fullscreen.png
CtfAllInOne2018124/img/loader.gif
CtfAllInOne2018124/img/menu-icon.png
CtfAllInOne2018124/img/save.png
CtfAllInOne2018124/img/saved.png
CtfAllInOne2018124/img/settings-s.png
CtfAllInOne2018124/img/settings.png
CtfAllInOne2018124/img/star.png
CtfAllInOne2018124/js/__init__.py
CtfAllInOne2018124/js/epub.js
CtfAllInOne2018124/js/epub.min.js
CtfAllInOne2018124/js/epub.min.map
CtfAllInOne2018124/js/hooks.min.js
CtfAllInOne2018124/js/hooks.min.map
CtfAllInOne2018124/js/reader.js
CtfAllInOne2018124/js/reader.js.map
CtfAllInOne2018124/js/reader.min.js
CtfAllInOne2018124/js/reader.min.map
CtfAllInOne2018124/js/hooks/__init__.py
CtfAllInOne2018124/js/hooks/extensions/__init__.py
CtfAllInOne2018124/js/hooks/extensions/highlight.js
CtfAllInOne2018124/js/libs/__init__.py
CtfAllInOne2018124/js/libs/jquery.min.js
CtfAllInOne2018124/js/libs/localforage.min.js
CtfAllInOne2018124/js/libs/screenfull.js
CtfAllInOne2018124/js/libs/screenfull.min.js
CtfAllInOne2018124/js/libs/zip.min.js
CtfAllInOne2018124/js/plugins/__init__.py
CtfAllInOne2018124/js/plugins/hypothesis.js
CtfAllInOne2018124/js/plugins/search.js
ctf_all_in_one_2018_1_24-2024.3.3.0.dist-info/METADATA
ctf_all_in_one_2018_1_24-2024.3.3.0.dist-info/WHEEL
ctf_all_in_one_2018_1_24-2024.3.3.0.dist-info/entry_points.txt
ctf_all_in_one_2018_1_24-2024.3.3.0.dist-info/top_level.txt
ctf_all_in_one_2018_1_24-2024.3.3.0.dist-info/RECORD
